setup.py
dj_crocodoc/__init__.py
dj_crocodoc/admin.py
dj_crocodoc/mixins.py
dj_crocodoc/models.py
dj_crocodoc/services.py
dj_crocodoc/signals.py
dj_crocodoc/urls.py
dj_crocodoc/views.py
django_crocodoc.egg-info/PKG-INFO
django_crocodoc.egg-info/SOURCES.txt
django_crocodoc.egg-info/dependency_links.txt
django_crocodoc.egg-info/requires.txt
django_crocodoc.egg-info/top_level.txt