Metadata-Version: 1.0
Name: django-crocodoc
Version: 0.1.2
Summary: Django app for integrating with CrocoDoc
Home-page: https://github.com/rosscdh/django-crocodoc
Author: Ross Crawford-d'Heureuse
Author-email: ross@lawpal.com
License: MIT
Keywords: django crocdoc app
Platform: UNKNOWN
